localized_message/__init__.py
localized_message-0.1.1.dist-info/licenses/LICENSE
localized_message-0.1.1.dist-info/METADATA
localized_message-0.1.1.dist-info/WHEEL
localized_message-0.1.1.dist-info/entry_points.txt
localized_message-0.1.1.dist-info/top_level.txt
localized_message-0.1.1.dist-info/RECORD
