Metadata-Version: 2.4
Name: localized_message
Version: 0.1.1
Summary: Python module to print messages according to the $LANG environment variable.
Author-email: Pablo Alejandro Carravetti <gpablinux@gmail.com>
License: GNU General Public License v3.0
Project-URL: Homepage, https://github.com/PabliNet/localized-message
License-File: LICENSE
Dynamic: license-file
